michelson_kernel/README.md
michelson_kernel/__init__.py
michelson_kernel/__main__.py
michelson_kernel/cli.py
michelson_kernel/docs.py
michelson_kernel/kernel.js
michelson_kernel/kernel.py
pymavryk/__init__.py
pymavryk/__main__.py
pymavryk/block/__init__.py
pymavryk/block/forge.py
pymavryk/block/header.py
pymavryk/cli/__init__.py
pymavryk/cli/__main__.py
pymavryk/cli/cli.py
pymavryk/cli/github.py
pymavryk/client.py
pymavryk/context/__init__.py
pymavryk/context/abstract.py
pymavryk/context/impl.py
pymavryk/context/mixin.py
pymavryk/contract/__init__.py
pymavryk/contract/call.py
pymavryk/contract/data.py
pymavryk/contract/entrypoint.py
pymavryk/contract/interface.py
pymavryk/contract/metadata-schema.json
pymavryk/contract/metadata.py
pymavryk/contract/result.py
pymavryk/contract/token_metadata-schema.json
pymavryk/contract/token_metadata.py
pymavryk/contract/view.py
pymavryk/crypto/__init__.py
pymavryk/crypto/encoding.py
pymavryk/crypto/hash.py
pymavryk/crypto/keccak.py
pymavryk/crypto/key.py
pymavryk/jupyter.py
pymavryk/logging.py
pymavryk/michelson/__init__.py
pymavryk/michelson/forge.py
pymavryk/michelson/format.py
pymavryk/michelson/instructions/__init__.py
pymavryk/michelson/instructions/adt.py
pymavryk/michelson/instructions/arithmetic.py
pymavryk/michelson/instructions/base.py
pymavryk/michelson/instructions/boolean.py
pymavryk/michelson/instructions/compare.py
pymavryk/michelson/instructions/control.py
pymavryk/michelson/instructions/crypto.py
pymavryk/michelson/instructions/generic.py
pymavryk/michelson/instructions/jupyter.py
pymavryk/michelson/instructions/mavryk.py
pymavryk/michelson/instructions/stack.py
pymavryk/michelson/instructions/struct.py
pymavryk/michelson/instructions/ticket.py
pymavryk/michelson/instructions/tzt.py
pymavryk/michelson/macros.py
pymavryk/michelson/micheline.py
pymavryk/michelson/parse.py
pymavryk/michelson/program.py
pymavryk/michelson/repl.py
pymavryk/michelson/sections/__init__.py
pymavryk/michelson/sections/code.py
pymavryk-3.12.2.dist-info/LICENSE
pymavryk-3.12.2.dist-info/METADATA
pymavryk-3.12.2.dist-info/WHEEL
pymavryk-3.12.2.dist-info/entry_points.txt
pymavryk-3.12.2.dist-info/RECORD
