Metadata-Version: 2.1
Name: pymavryk
Version: 3.12.2
Summary: Python toolkit for Mavryk
Home-page: https://pymavryk.mavryk.org
License: MIT
Keywords: mavryk,blockchain,sdk,michelson,repl,cryptocurrencies,smart-contracts,jupyter,ipython,docker,crypto
Author: Michael Zaikin
Author-email: mz@baking-bad.org
Maintainer: Tristan Allaire
Maintainer-email: tristan@mavryk.io
Requires-Python: >=3.8.1,<3.13
Classifier: Development Status :: 5 - Production/Stable
Classifier: Environment :: Console
Classifier: Framework :: IPython
Classifier: Intended Audience :: Developers
Classifier: License :: OSI Approved :: MIT License
Classifier: Operating System :: OS Independent
Classifier: Programming Language :: Python :: 3
Classifier: Programming Language :: Python :: 3.9
Classifier: Programming Language :: Python :: 3.10
Classifier: Programming Language :: Python :: 3.11
Classifier: Programming Language :: Python :: 3.12
Classifier: Programming Language :: Python :: 3.8
Classifier: Programming Language :: Python :: Implementation :: CPython
Classifier: Topic :: Software Development :: Libraries :: Application Frameworks
Classifier: Typing :: Typed
Requires-Dist: attrs (>=21.4.0)
Requires-Dist: base58 (>=2.1.1,<3.0.0)
Requires-Dist: cattrs (>=22.1.0)
Requires-Dist: click (>=8.1.3,<9.0.0)
Requires-Dist: cryptography (>=42.0.4)
Requires-Dist: deprecation (>=2.1.0,<3.0.0)
Requires-Dist: docker (>=6.0.0,<7.0.0)
Requires-Dist: fastecdsa (>=2.2.3,<3.0.0)
Requires-Dist: jsonschema (>=4.3.2,<5.0.0)
Requires-Dist: mnemonic (>=0.21,<0.22)
Requires-Dist: netstruct (>=1.1.2,<2.0.0)
Requires-Dist: notebook (>=6.5.6,<7.0.0)
Requires-Dist: ply (>=3.11,<4.0)
Requires-Dist: py-ecc (>=7.0.0,<8.0.0)
Requires-Dist: pysodium (>=0.7.10,<0.8.0)
Requires-Dist: python-dateutil (>=2.8.2,<3.0.0)
Requires-Dist: requests (>=2.28.2,<2.32.0)
Requires-Dist: secp256k1 (>=0.14.0,<0.15.0)
Requires-Dist: setuptools (>=69.0.0,<70.0.0)
Requires-Dist: simple-bson (>=0.0.3,<0.0.4)
Requires-Dist: simplejson (>=3.17.6,<4.0.0)
Requires-Dist: strict-rfc3339 (>=0.7,<0.8)
Requires-Dist: tabulate (>=0.9.0,<0.10.0)
Requires-Dist: testcontainers (>=3.7.0,<4.0.0)
Requires-Dist: tqdm (>=4.62.3,<5.0.0)
Project-URL: Repository, https://github.com/mavryk-network/pymavryk
